setup.py
enplot/__init__.py
enplot/base.py
enplot/run.py
enplot/version.py
enplot.egg-info/PKG-INFO
enplot.egg-info/SOURCES.txt
enplot.egg-info/dependency_links.txt
enplot.egg-info/entry_points.txt
enplot.egg-info/top_level.txt