Metadata-Version: 1.0
Name: enplot
Version: 1.0.1
Summary: enplot: a one-line command line plotting tool for CSV data
Home-page: http://github.com/jrjohansson
Author: Robert Johansson
Author-email: jrjohansson@gmail.com
License: LGPL
Keywords: plotting,one-line,command-line
Platform: Linux
Platform: Unix
